fiicha/__init__.py
fiicha/context.py
fiicha/core.py
fiicha/doc.py
fiicha/parser.py
fiicha/py.typed
fiicha/utils.py
fiicha-0.2.0.dist-info/LICENSE
fiicha-0.2.0.dist-info/METADATA
fiicha-0.2.0.dist-info/WHEEL
fiicha-0.2.0.dist-info/top_level.txt
fiicha-0.2.0.dist-info/RECORD
