Metadata-Version: 2.1
Name: fiicha
Version: 0.2.0
Summary: A minimalistic feature flag implementation with type hints.
Home-page: https://github.com/ZipFile/fiicha
Author: Anatolii Aniskovych
Author-email: lin.aaa.lin@gmail.com
License: BSD 2-Clause License
Keywords: feature flags
Platform: UNKNOWN
Classifier: Development Status :: 3 - Alpha
Classifier: Intended Audience :: Developers
Classifier: License :: OSI Approved :: BSD License
Classifier: Programming Language :: Python :: 3
Classifier: Programming Language :: Python :: 3.8
Classifier: Programming Language :: Python :: 3.9
Classifier: Programming Language :: Python :: 3.10
Classifier: Topic :: Utilities
License-File: LICENSE
Provides-Extra: lint
Requires-Dist: black ; extra == 'lint'
Requires-Dist: flake8 ; extra == 'lint'
Requires-Dist: flake8-print ; extra == 'lint'
Requires-Dist: isort ; extra == 'lint'
Requires-Dist: mypy ; extra == 'lint'
Provides-Extra: test
Requires-Dist: pytest ; extra == 'test'
Requires-Dist: pytest-cov ; extra == 'test'
